{
  "parent": "minecraft:recipes/root",
  "rewards": {
    "recipes": [
      "gemspark:cosmetic_clay"
    ]
  },
  "criteria": {
    "has_clay": {
      "trigger": "minecraft:inventory_changed",
      "conditions": {
        "items": [
          {
            "items": [
              "minecraft:clay"
            ]
          }
        ]
      }
    },
    "has_the_recipe": {
      "trigger": "minecraft:recipe_unlocked",
      "conditions": {
        "recipe": "gemspark:cosmetic_clay"
      }
    }
  },
  "requirements": [
    [
      "has_clay",
      "has_the_recipe"
    ]
  ]
}